questionary_cli/__init__.py
questionary_cli/__version__.py
questionary_cli/cli.py
questionary_cli/py.typed
questionary_cli-0.1.2.dist-info/METADATA
questionary_cli-0.1.2.dist-info/WHEEL
questionary_cli-0.1.2.dist-info/entry_points.txt
questionary_cli-0.1.2.dist-info/licenses/LICENSE
questionary_cli-0.1.2.dist-info/RECORD
