Metadata-Version: 2.4
Name: questionary-cli
Version: 0.1.2
Summary: Command line tool for questionary.
Project-URL: Documentation, https://github.com/makukha/questionary-cli#readme
Project-URL: Homepage, https://github.com/makukha/questionary-cli
Project-URL: Repository, https://github.com/makukha/questionary-cli
Project-URL: Issues, https://github.com/makukha/questionary-cli/issues
Project-URL: Changelog, https://github.com/makukha/questionary-cli/blob/main/CHANGELOG.md
Author-email: Michael Makukha <m.makukha@gmail.com>
License: MIT
License-File: LICENSE
Keywords: cli,command,prompt,questionary
Classifier: Development Status :: 4 - Beta
Classifier: Intended Audience :: Developers
Classifier: License :: OSI Approved :: MIT License
Classifier: Operating System :: OS Independent
Classifier: Programming Language :: Python
Classifier: Programming Language :: Python :: 3
Classifier: Programming Language :: Python :: 3.10
Classifier: Programming Language :: Python :: 3.11
Classifier: Programming Language :: Python :: 3.12
Classifier: Programming Language :: Python :: 3.13
Classifier: Programming Language :: Python :: Implementation :: CPython
Classifier: Topic :: Documentation
Classifier: Topic :: Software Development
Classifier: Topic :: Software Development :: Libraries
Classifier: Typing :: Typed
Requires-Python: >=3.10
Requires-Dist: questionary>=2
Requires-Dist: rich-click>=1.8
Requires-Dist: typing-extensions>=4
